flowgen/__init__.py
flowgen-0.0.1.dist-info/licenses/LICENSE
flowgen-0.0.1.dist-info/METADATA
flowgen-0.0.1.dist-info/WHEEL
flowgen-0.0.1.dist-info/top_level.txt
flowgen-0.0.1.dist-info/RECORD
