Metadata-Version: 2.4
Name: flowgen
Version: 0.0.1
Summary: Flow-Based Generative Modeling
Author-email: Chiatse Wang <chiatsewang@stat.sinica.edu.tw>
License: MIT
Project-URL: Homepage, https://github.com/chiatsewang/flowgen
Project-URL: Source, https://github.com/chiatsewang/flowgen
Project-URL: Issues, https://github.com/chiatsewang/flowgen/issues
Keywords: generative modeling,flow-based models,machine learning,deep learning
Classifier: Development Status :: 3 - Alpha
Classifier: Intended Audience :: Developers
Classifier: Intended Audience :: Science/Research
Classifier: License :: OSI Approved :: MIT License
Classifier: Programming Language :: Python :: 3
Classifier: Programming Language :: Python :: 3.10
Classifier: Programming Language :: Python :: 3.11
Classifier: Topic :: Scientific/Engineering :: Artificial Intelligence
Requires-Python: >=3.10
License-File: LICENSE
Dynamic: license-file
